{"cameraMode":{"drawMode":0,"name":"Shaded","section":"Shading Mode"},"sceneLighting":true,"audioPlay":false,"sceneViewState":{"showFog":true,"showMaterialUpdate":false,"showSkybox":true,"showFlares":true,"showImageEffects":true,"showParticleSystems":true},"in2DMode":false,"pivot":{"x":198.22271728515626,"y":-182.2688446044922,"z":245.8206329345703},"rotation":{"x":0.2404240369796753,"y":0.3377722501754761,"z":-0.08967385441064835,"w":0.9056001305580139},"size":201.98995971679688,"orthographic":false}